coingecko_openapi_client
test
