Metadata-Version: 2.1
Name: coingecko-openapi-client
Version: 1.1.0
Summary: CoinGecko API V3
Home-page: https://github.com/Drakkar-Software/coingecko-openapi-clients
Author-email: 
Keywords: Swagger,CoinGecko API V3
